LICENSE
MANIFEST.in
README.md
requirements.txt
setup.py
antlr_plsql/__init__.py
antlr_plsql/ast.py
antlr_plsql/speaker.yml
antlr_plsql.egg-info/PKG-INFO
antlr_plsql.egg-info/SOURCES.txt
antlr_plsql.egg-info/dependency_links.txt
antlr_plsql.egg-info/requires.txt
antlr_plsql.egg-info/top_level.txt
antlr_plsql/antlr_py/__init__.py
antlr_plsql/antlr_py/plsql.interp
antlr_plsql/antlr_py/plsql.tokens
antlr_plsql/antlr_py/plsqlLexer.interp
antlr_plsql/antlr_py/plsqlLexer.py
antlr_plsql/antlr_py/plsqlLexer.tokens
antlr_plsql/antlr_py/plsqlListener.py
antlr_plsql/antlr_py/plsqlParser.py
antlr_plsql/antlr_py/plsqlVisitor.py